getmonitorresolution/README.md
getmonitorresolution/__init__.py
getmonitorresolution/requirements.txt
getmonitorresolution/thirdparty.json
getmonitorresolution-0.13.dist-info/LICENSE.rst
getmonitorresolution-0.13.dist-info/METADATA
getmonitorresolution-0.13.dist-info/WHEEL
getmonitorresolution-0.13.dist-info/top_level.txt
getmonitorresolution-0.13.dist-info/RECORD
