Metadata-Version: 2.1
Name: getmonitorresolution
Version: 0.13
Summary: Uses ctypes to get the resolution information of all available monitors
Home-page: https://github.com/hansalemaos/getmonitorresolution
Author: Johannes Fischer
Author-email: aulasparticularesdealemaosp@gmail.com
License: MIT
Keywords: ctypes,monitor,resolution
Classifier: Development Status :: 4 - Beta
Classifier: Programming Language :: Python :: 3 :: Only
Classifier: Programming Language :: Python :: 3.10
Classifier: Topic :: Software Development :: Libraries :: Python Modules
Classifier: Topic :: Utilities
License-File: LICENSE.rst
Requires-Dist: flatten-any-dict-iterable-or-whatsoever
